{
  "common_name": "Ruby-crowned Kinglet",
  "scientific_name": "Regulus calendula",
  "sex": "female",
  "life_stage": "adult",
  "captive": false,
  "photo_id": 658361670,
  "attribution": "(c) sko_tang, some rights reserved (CC BY-NC)",
  "license": "cc-by-nc",
  "obs_url": "https://www.inaturalist.org/observations/360779513",
  "obs_date": "2026-05-11",
  "recorded_by": "sko_tang",
  "download_url": "https://inaturalist-open-data.s3.amazonaws.com/photos/658361670/medium.jpg",
  "size_kb": 150.0,
  "local_file": "9_658361670.jpg"
}