{
  "common_name": "Golden-crowned Sparrow",
  "scientific_name": "Zonotrichia atricapilla",
  "sex": "male",
  "life_stage": "adult",
  "captive": false,
  "photo_id": 638729377,
  "attribution": "(c) Chris Evers, some rights reserved (CC BY-NC)",
  "license": "cc-by-nc",
  "obs_url": "https://www.inaturalist.org/observations/350097247",
  "obs_date": "2026-04-12",
  "recorded_by": "cae1",
  "download_url": "https://inaturalist-open-data.s3.amazonaws.com/photos/638729377/medium.jpg",
  "size_kb": 150.0,
  "local_file": "10_638729377.jpg"
}