{
  "common_name": "Palm Warbler",
  "scientific_name": "Setophaga palmarum",
  "sex": "male",
  "life_stage": "adult",
  "captive": false,
  "photo_id": 658383727,
  "attribution": "(c) Jessica, all rights reserved",
  "license": null,
  "obs_url": "https://www.inaturalist.org/observations/360790645",
  "obs_date": "2026-05-11",
  "recorded_by": "chasing_raptors",
  "download_url": "https://static.inaturalist.org/photos/658383727/medium.jpg",
  "size_kb": 150.0,
  "local_file": "8_658383727.jpg"
}