{
  "common_name": "Solitary Sandpiper",
  "scientific_name": "Tringa solitaria",
  "sex": "male",
  "life_stage": "adult",
  "captive": false,
  "photo_id": 95233372,
  "attribution": "(c) Susan Elliott, some rights reserved (CC BY-NC)",
  "license": "cc-by-nc",
  "obs_url": "https://www.inaturalist.org/observations/59596353",
  "obs_date": "2020-09-14",
  "recorded_by": "susanelliott",
  "download_url": "https://inaturalist-open-data.s3.amazonaws.com/photos/95233372/medium.jpg",
  "size_kb": 150.0,
  "local_file": "1_95233372.jpg"
}