{
  "common_name": "White-throated Sparrow",
  "scientific_name": "Zonotrichia albicollis",
  "sex": "female",
  "life_stage": "adult",
  "captive": false,
  "photo_id": 656649484,
  "attribution": "(c) Karl Kroeker, some rights reserved (CC BY-NC)",
  "license": "cc-by-nc",
  "obs_url": "https://www.inaturalist.org/observations/359882101",
  "obs_date": "2026-05-09",
  "recorded_by": "kkrockytop",
  "download_url": "https://inaturalist-open-data.s3.amazonaws.com/photos/656649484/medium.jpg",
  "size_kb": 150.0,
  "local_file": "9_656649484.jpg"
}