{
  "common_name": "Bank Swallow",
  "scientific_name": "Riparia riparia",
  "sex": "male",
  "life_stage": "adult",
  "captive": false,
  "photo_id": 648361264,
  "attribution": "(c) Мельничук Світлана, some rights reserved (CC BY-NC)",
  "license": "cc-by-nc",
  "obs_url": "https://www.inaturalist.org/observations/355521169",
  "obs_date": "2026-04-27",
  "recorded_by": "svetlanamelnychuk",
  "download_url": "https://inaturalist-open-data.s3.amazonaws.com/photos/648361264/medium.jpg",
  "size_kb": 150.0,
  "local_file": "5_648361264.jpg"
}